nl_maps/__init__.py
nl_maps/nl_config.py
nl_maps/nl_data.py
nl_maps/nl_maps.py
nl_maps/source/LICENSE_ISLANDS_PROVINCES
nl_maps/source/LICENSE_MUNICIPALITIES
nl_maps/source/MODIFICATIONS.md
nl_maps/source/bes_islands.png
nl_maps/source/nl_municipalities.png
nl_maps/source/nl_provinces.png
nl_maps-0.2.0.dist-info/METADATA
nl_maps-0.2.0.dist-info/WHEEL
nl_maps-0.2.0.dist-info/licenses/LICENSE
nl_maps-0.2.0.dist-info/RECORD
