Metadata-Version: 2.3
Name: nl_maps
Version: 0.2.0
Summary: Create informative maps of the Netherlands, including the BES islands.
Project-URL: Homepage, https://github.com/debruijn/nl_maps
Project-URL: Bug Tracker, https://github.com/debruijn/nl_maps/issues
Author-email: Bert de Bruijn <lpdebruijn@gmail.com>
License: MIT License
License-File: LICENSE
Classifier: License :: OSI Approved :: MIT License
Classifier: Operating System :: OS Independent
Classifier: Programming Language :: Python :: 3
Requires-Python: >=3.10
Requires-Dist: pillow
